chronos/__init__.py
chronos/chronos.py
py_quantize_chronos-0.1.8.dist-info/LICENSE
py_quantize_chronos-0.1.8.dist-info/METADATA
py_quantize_chronos-0.1.8.dist-info/WHEEL
py_quantize_chronos-0.1.8.dist-info/top_level.txt
py_quantize_chronos-0.1.8.dist-info/RECORD
