Metadata-Version: 2.1
Name: py-quantize-chronos
Version: 0.1.8
Summary: utility tool that analyzes symbolic runtime of python functions
Home-page: https://github.com/h3x4g0ns/py-chronos/tree/main
Author: Ekansh Agrawal
Author-email: agrawalekansh@berkeley.edu
Keywords: python,runtime,cli
Classifier: Programming Language :: Python :: 3
Classifier: License :: OSI Approved :: MIT License
Classifier: Operating System :: OS Independent
Requires-Python: >=3.7
License-File: LICENSE
Requires-Dist: numpy
Requires-Dist: tqdm
